timmins_sort/CTVisualizer.py
timmins_sort/Vis_Sort.py
timmins_sort/__init__.py
timmins_sort/command_line.py
timmins_sort/ct_algorithms.py
timmins_sort-1.1.0.dist-info/METADATA
timmins_sort-1.1.0.dist-info/WHEEL
timmins_sort-1.1.0.dist-info/entry_points.txt
timmins_sort-1.1.0.dist-info/top_level.txt
timmins_sort-1.1.0.dist-info/RECORD
