Metadata-Version: 2.1
Name: timmins-sort
Version: 1.1.0
Home-page: https://github.com/ctimmins96/Sorting-Algorithm-Visualizer
Author: Chase Timmins (a.k.a. OmegaBumBum, BumBum the Grand, and Giggle B*tch)
Author-email: chase.timmins@gmail.com
Requires-Dist: pygame (==2.1.2)
